aipseo/__init__.py
aipseo/api.py
aipseo/cli.py
aipseo/common.py
aipseo/utils.py
aipseo/commands/__init__.py
aipseo/commands/init.py
aipseo/commands/lookup.py
aipseo/commands/market.py
aipseo/commands/spam_score.py
aipseo/commands/validate.py
aipseo/commands/wallet.py
aipseo-0.2.0.dist-info/METADATA
aipseo-0.2.0.dist-info/WHEEL
aipseo-0.2.0.dist-info/entry_points.txt
aipseo-0.2.0.dist-info/RECORD
