Metadata-Version: 2.4
Name: aipseo
Version: 0.2.0
Summary: Command-line interface for AI powered SEO backlinks
Project-URL: Homepage, https://github.com/aipseo/aipseo
Project-URL: Repository, https://github.com/aipseo/aipseo.git
Project-URL: Documentation, https://github.com/aipseo/aipseo#readme
Project-URL: Issues, https://github.com/aipseo/aipseo/issues
Author-email: Mark Counterman <ilovepoker@gmail.com>
License: Apache-2.0
Classifier: Development Status :: 5 - Production/Stable
Classifier: Intended Audience :: Developers
Classifier: License :: OSI Approved :: Apache Software License
Classifier: Programming Language :: Python :: 3
Classifier: Programming Language :: Python :: 3.8
Classifier: Programming Language :: Python :: 3.9
Classifier: Programming Language :: Python :: 3.10
Classifier: Programming Language :: Python :: 3.11
Requires-Python: >=3.8
Requires-Dist: cryptography>=41.0.0
Requires-Dist: jsonschema>=4.17.0
Requires-Dist: pydantic>=2.0.0
Requires-Dist: requests>=2.28.0
Requires-Dist: rich>=12.0.0
Requires-Dist: stripe>=5.4.0
Requires-Dist: typer>=0.9.0
Requires-Dist: urllib3>=2.0.0
